pyfoo
