Metadata-Version: 2.1
Name: pyfoo
Version: 0.1.3
Summary: Testing...
Home-page: https://github.com/dingraha/pyfoo
Author: Daniel Ingraham
Author-email: d.j.ingraham@gmail.com
License: MIT
Platform: UNKNOWN
